localgraphclustering/GraphDrawing.py
localgraphclustering/GraphLocal.py
localgraphclustering/MQI.py
localgraphclustering/MQI_weighted.py
localgraphclustering/SimpleLocal.py
localgraphclustering/SimpleLocal_weighted.py
localgraphclustering/__init__.py
localgraphclustering/approximate_PageRank.py
localgraphclustering/approximate_PageRank_weighted.py
localgraphclustering/capacity_releasing_diffusion.py
localgraphclustering/densest_subgraph.py
localgraphclustering/fiedler.py
localgraphclustering/find_clusters.py
localgraphclustering/flow_clustering.py
localgraphclustering/multiclass_label_prediction.py
localgraphclustering/ncp.py
localgraphclustering/ncpplots.py
localgraphclustering/neighborhoodmin.py
localgraphclustering/pageRank_nibble.py
localgraphclustering/spectral_clustering.py
localgraphclustering/sweep_cut.py
localgraphclustering/test.py
localgraphclustering/triangleclusters.py
localgraphclustering/algorithms/__init__.py
localgraphclustering/algorithms/acl_list.py
localgraphclustering/algorithms/eig2_nL.py
localgraphclustering/algorithms/fista_dinput_dense.py
localgraphclustering/algorithms/sweepcut.py
localgraphclustering/cpp/MQI_cpp.py
localgraphclustering/cpp/MQI_weighted_cpp.py
localgraphclustering/cpp/SimpleLocal_cpp.py
localgraphclustering/cpp/SimpleLocal_weighted_cpp.py
localgraphclustering/cpp/__init__.py
localgraphclustering/cpp/aclpagerank_cpp.py
localgraphclustering/cpp/aclpagerank_weighted_cpp.py
localgraphclustering/cpp/capacity_releasing_diffusion_cpp.py
localgraphclustering/cpp/densest_subgraph_cpp.py
localgraphclustering/cpp/proxl1PRaccel.py
localgraphclustering/cpp/proxl1PRrand_cpp.py
localgraphclustering/cpp/set_scores_cpp.py
localgraphclustering/cpp/sweepcut_cpp.py
localgraphclustering/cpp/triangleclusters_cpp.py
localgraphclustering/cpp/utility.py
localgraphclustering/src/.gitignore
localgraphclustering/src/graph/Erdos02-cc.smat
localgraphclustering/src/graph/JohnHopkins.smat
localgraphclustering/src/graph/Unknown.smat
localgraphclustering-0.6.0.dist-info/LICENSE.txt
localgraphclustering-0.6.0.dist-info/METADATA
localgraphclustering-0.6.0.dist-info/WHEEL
localgraphclustering-0.6.0.dist-info/top_level.txt
localgraphclustering-0.6.0.dist-info/RECORD
