Metadata-Version: 2.1
Name: localgraphclustering
Version: 0.6.0
Summary: Package for local graph clustering
Home-page: https://github.com/kfoynt/LocalGraphClustering
Author: Kimon Fountoulakis, Meng Liu, David Gleich, Michael W. Mahoney
Author-email: kimon.fountoulakis@uwaterloo.ca
License: GPL
Keywords: local graph clustering
Platform: UNKNOWN
Classifier: Development Status :: 3 - Alpha
Classifier: License :: OSI Approved :: GNU General Public License (GPL)
Classifier: Programming Language :: Python :: 3.5
Requires-Dist: numpy (>=1.12.0)
Requires-Dist: scipy (>=0.18.1)
Requires-Dist: networkx (>=1.11)
Requires-Dist: matplotlib (>=2.0.0)
Requires-Dist: typing
Requires-Dist: matplotlib
Requires-Dist: pandas
Requires-Dist: plotly
Requires-Dist: sklearn
Requires-Dist: joblib
